[{"back": "./imgs/cards/000-back.png", "front": "./imgs/cards/000-front.png", "name": "Void", "number": 0}, {"back": "./imgs/cards/001-back.png", "front": "./imgs/cards/001-front.png", "name": "Justice", "number": 1}, {"back": "./imgs/cards/002-back.png", "front": "./imgs/cards/002-front.png", "name": "Strength", "number": 2}, {"back": "./imgs/cards/003-back.png", "front": "./imgs/cards/003-front.png", "name": "Death", "number": 3}, {"back": "./imgs/cards/004-back.png", "front": "./imgs/cards/004-front.png", "name": "The Wall", "number": 4}, {"back": "./imgs/cards/005-back.png", "front": "./imgs/cards/005-front.png", "name": "Temperance", "number": 5}, {"back": "./imgs/cards/006-back.png", "front": "./imgs/cards/006-front.png", "name": "Branch", "number": 6}, {"back": "./imgs/cards/007-back.png", "front": "./imgs/cards/007-front.png", "name": "The Hanged Man", "number": 7}, {"back": "./imgs/cards/008-back.png", "front": "./imgs/cards/008-front.png", "name": "The High Priestess", "number": 8}, {"back": "./imgs/cards/009-back.png", "front": "./imgs/cards/009-front.png", "name": "The Moon", "number": 9}, {"back": "./imgs/cards/010-back.png", "front": "./imgs/cards/010-front.png", "name": "The Emperor", "number": 10}, {"back": "./imgs/cards/011-back.png", "front": "./imgs/cards/011-front.png", "name": "The Hierophant", "number": 11}, {"back": "./imgs/cards/012-back.png", "front": "./imgs/cards/012-front.png", "name": "The Tower", "number": 12}, {"back": "./imgs/cards/013-back.png", "front": "./imgs/cards/013-front.png", "name": "Merge", "number": 13}, {"back": "./imgs/cards/014-back.png", "front": "./imgs/cards/014-front.png", "name": "Hope", "number": 14}, {"back": "./imgs/cards/015-back.png", "front": "./imgs/cards/015-front.png", "name": "The Temple", "number": 15}, {"back": "./imgs/cards/016-back.png", "front": "./imgs/cards/016-front.png", "name": "The Summit", "number": 16}, {"back": "./imgs/cards/017-back.png", "front": "./imgs/cards/017-front.png", "name": "The Diamond", "number": 17}, {"back": "./imgs/cards/018-back.png", "front": "./imgs/cards/018-front.png", "name": "The Hermit", "number": 18}, {"back": "./imgs/cards/019-back.png", "front": "./imgs/cards/019-front.png", "name": "Intuition", "number": 19}, {"back": "./imgs/cards/020-back.png", "front": "./imgs/cards/020-front.png", "name": "The Stone", "number": 20}, {"back": "./imgs/cards/021-back.png", "front": "./imgs/cards/021-front.png", "name": "The Mountain", "number": 21}, {"back": "./imgs/cards/022-back.png", "front": "./imgs/cards/022-front.png", "name": "The Shadow", "number": 22}, {"back": "./imgs/cards/023-back.png", "front": "./imgs/cards/023-front.png", "name": "Opposite", "number": 23}, {"back": "./imgs/cards/024-back.png", "front": "./imgs/cards/024-front.png", "name": "The Oak", "number": 24}, {"back": "./imgs/cards/025-back.png", "front": "./imgs/cards/025-front.png", "name": "Ripples", "number": 25}, {"back": "./imgs/cards/026-back.png", "front": "./imgs/cards/026-front.png", "name": "The Empress", "number": 26}, {"back": "./imgs/cards/027-back.png", "front": "./imgs/cards/027-front.png", "name": "Bundle", "number": 27}, {"back": "./imgs/cards/028-back.png", "front": "./imgs/cards/028-front.png", "name": "The Devil", "number": 28}, {"back": "./imgs/cards/029-back.png", "front": "./imgs/cards/029-front.png", "name": "The Sun", "number": 29}, {"back": "./imgs/cards/030-back.png", "front": "./imgs/cards/030-front.png", "name": "The Star", "number": 30}, {"back": "./imgs/cards/031-back.png", "front": "./imgs/cards/031-front.png", "name": "Judgement", "number": 31}, {"back": "./imgs/cards/032-back.png", "front": "./imgs/cards/032-front.png", "name": "Wheel of Fortune", "number": 32}, {"back": "./imgs/cards/033-back.png", "front": "./imgs/cards/033-front.png", "name": "Vision", "number": 33}, {"back": "./imgs/cards/034-back.png", "front": "./imgs/cards/034-front.png", "name": "The Lovers", "number": 34}, {"back": "./imgs/cards/035-back.png", "front": "./imgs/cards/035-front.png", "name": "The Magician", "number": 35}, {"back": "./imgs/cards/036-back.png", "front": "./imgs/cards/036-front.png", "name": "The Link", "number": 36}, {"back": "./imgs/cards/037-back.png", "front": "./imgs/cards/037-front.png", "name": "Holding Together", "number": 37}, {"back": "./imgs/cards/038-back.png", "front": "./imgs/cards/038-front.png", "name": "The Chariot", "number": 38}, {"back": "./imgs/cards/039-back.png", "front": "./imgs/cards/039-front.png", "name": "The Loop", "number": 39}, {"back": "./imgs/cards/040-back.png", "front": "./imgs/cards/040-front.png", "name": "Turning point", "number": 40}, {"back": "./imgs/cards/041-back.png", "front": "./imgs/cards/041-front.png", "name": "Trinity", "number": 41}, {"back": "./imgs/cards/042-back.png", "front": "./imgs/cards/042-front.png", "name": "The Cauldron", "number": 42}, {"back": "./imgs/cards/043-back.png", "front": "./imgs/cards/043-front.png", "name": "The Elders", "number": 43}, {"back": "./imgs/cards/044-back.png", "front": "./imgs/cards/044-front.png", "name": "The Core", "number": 44}, {"back": "./imgs/cards/045-back.png", "front": "./imgs/cards/045-front.png", "name": "Inner Truth", "number": 45}, {"back": "./imgs/cards/046-back.png", "front": "./imgs/cards/046-front.png", "name": "The World", "number": 46}, {"back": "./imgs/cards/047-back.png", "front": "./imgs/cards/047-front.png", "name": "The Fool", "number": 47}, {"back": "./imgs/cards/048-back.png", "front": "./imgs/cards/048-front.png", "name": "Enlightenment", "number": 48}]